cogniweave/__init__.py
cogniweave/__main__.py
cogniweave/config.py
cogniweave/prompts.py
cogniweave/py.typed
cogniweave/quickstart.py
cogniweave/typing.py
cogniweave/utils.py
cogniweave/cli/__init__.py
cogniweave/core/__init__.py
cogniweave/core/end_detector/__init__.py
cogniweave/core/memory_maker/__init__.py
cogniweave/core/memory_maker/long_memory.py
cogniweave/core/memory_maker/short_memory.py
cogniweave/core/memory_maker/summary.py
cogniweave/core/prompt_values/__init__.py
cogniweave/core/prompt_values/end_detector.py
cogniweave/core/prompt_values/long_memory.py
cogniweave/core/prompt_values/short_memory.py
cogniweave/core/prompt_values/values/__init__.py
cogniweave/core/prompt_values/values/end_detector.py
cogniweave/core/prompt_values/values/long_memory.py
cogniweave/core/prompt_values/values/short_memory.py
cogniweave/core/prompts/__init__.py
cogniweave/core/prompts/long_memory.py
cogniweave/core/prompts/short_memory.py
cogniweave/core/runnables/__init__.py
cogniweave/core/runnables/end_detector.py
cogniweave/core/runnables/history_store.py
cogniweave/core/runnables/memory_maker.py
cogniweave/core/time_splitter/__init__.py
cogniweave/core/time_splitter/base.py
cogniweave/core/time_splitter/manager.py
cogniweave/core/time_splitter/splitter.py
cogniweave/history_stores/__init__.py
cogniweave/history_stores/base.py
cogniweave/history_stores/cache.py
cogniweave/history_stores/models.py
cogniweave/llms/__init__.py
cogniweave/llms/base.py
cogniweave/llms/chat.py
cogniweave/prompt_values/__init__.py
cogniweave/prompt_values/base.py
cogniweave/prompt_values/default.py
cogniweave/vector_stores/__init__.py
cogniweave/vector_stores/base.py
cogniweave/vector_stores/meta.py
cogniweave/vector_stores/tags.py
cogniweave-0.1.10.dist-info/METADATA
cogniweave-0.1.10.dist-info/WHEEL
cogniweave-0.1.10.dist-info/licenses/LICENSE
cogniweave-0.1.10.dist-info/RECORD
