Metadata-Version: 2.4
Name: cogniweave
Version: 0.1.10
Summary: Experimental agent framework built on top of LangChain
Project-URL: Repository, https://github.com/Inexplicable-YL/CogniWeaveAgent
Author-email: Kotodama <2682064633@qq.com>
License: Apache License 2.0
License-File: LICENSE
Keywords: agent
Classifier: Development Status :: 3 - Alpha
Classifier: Intended Audience :: Developers
Classifier: License :: OSI Approved :: Apache Software License
Classifier: Programming Language :: Python :: 3
Classifier: Programming Language :: Python :: 3 :: Only
Requires-Python: <4,>=3.11
Requires-Dist: aiohttp==3.12.14
Requires-Dist: aiosqlite==0.21.0
Requires-Dist: anyio==4.9.0
Requires-Dist: exceptiongroup==1.2.2
Requires-Dist: faiss-cpu==1.11.0
Requires-Dist: httpx[socks]
Requires-Dist: langchain-community==0.3.25
Requires-Dist: langchain-core==0.3.68
Requires-Dist: langchain-openai==0.3.27
Requires-Dist: langchain==0.3.26
Requires-Dist: pyahocorasick==2.1.0
Requires-Dist: pydantic==2.11.7
Requires-Dist: pygtrie==2.5.0
Requires-Dist: pypinyin==0.54.0
Requires-Dist: python-dotenv
Requires-Dist: pyyaml==6.0.2
Requires-Dist: rich==14.0.0
Requires-Dist: sortedcontainers==2.4.0
Requires-Dist: sqlalchemy==2.0.41
Requires-Dist: typing-extensions==4.14.1
